dgg_chat_bot/__init__.py
dgg_chat_bot/_commands.py
dgg_chat_bot/_dgg_chat_bot.py
dgg_chat_bot/_utils.py
dgg_chat_bot/exceptions/__init__.py
dgg_chat_bot/exceptions/_exceptions.py
dgg_chat_bot/logging/__init__.py
dgg_chat_bot-0.1.10a0.dist-info/LICENSE
dgg_chat_bot-0.1.10a0.dist-info/METADATA
dgg_chat_bot-0.1.10a0.dist-info/WHEEL
dgg_chat_bot-0.1.10a0.dist-info/top_level.txt
dgg_chat_bot-0.1.10a0.dist-info/RECORD
