Metadata-Version: 2.1
Name: dgg-chat-bot
Version: 0.1.10a0
Summary: Build chat bots for the destiny.gg chat
Home-page: https://github.com/gabrieljablonski/dgg-chat-bot
Author: Gabriel Jablonski
Author-email: contact@gabrieljablonski.com
License: MIT
Keywords: chat-bot,chat,destinygg,dgg
Platform: UNKNOWN
Classifier: Development Status :: 3 - Alpha
Classifier: Intended Audience :: Developers
Classifier: License :: OSI Approved :: MIT License
Classifier: Programming Language :: Python :: 3.8
Requires-Python: >=3.8
Requires-Dist: dgg-chat
